napalm_procurve/__init__.py
napalm_procurve/procurve.py
napalm_procurve/utils/__init__.py
napalm_procurve-0.6.0.dist-info/AUTHORS
napalm_procurve-0.6.0.dist-info/LICENSE
napalm_procurve-0.6.0.dist-info/METADATA
napalm_procurve-0.6.0.dist-info/WHEEL
napalm_procurve-0.6.0.dist-info/top_level.txt
napalm_procurve-0.6.0.dist-info/RECORD
