Metadata-Version: 2.1
Name: napalm-procurve
Version: 0.6.0
Summary: Network Automation and Programmability Abstraction Layer (NAPALM) ProCurve driver
Home-page: https://github.com/ixs/napalm-procurve
Author: Andreas Thienemann
Author-email: andreas@bawue.net
License: UNKNOWN
Platform: UNKNOWN
Classifier: Topic :: Utilities
Classifier: Programming Language :: Python
Classifier: Programming Language :: Python :: 3
Classifier: Operating System :: POSIX :: Linux
Classifier: Operating System :: MacOS
Requires-Dist: napalm (>=3.0.0)
Requires-Dist: netmiko
